tolkein/__init__.py
tolkein/__main__.py
tolkein/tolkein.py
tolkein/lib/__init__.py
tolkein/lib/tobin.py
tolkein/lib/tofetch.py
tolkein/lib/tofile.py
tolkein/lib/toinsdc.py
tolkein/lib/tolog.py
tolkein/lib/tostats.py
tolkein/lib/totax.py
tolkein/lib/version.py
tolkein-0.5.0.dist-info/AUTHORS.rst
tolkein-0.5.0.dist-info/LICENSE
tolkein-0.5.0.dist-info/METADATA
tolkein-0.5.0.dist-info/WHEEL
tolkein-0.5.0.dist-info/entry_points.txt
tolkein-0.5.0.dist-info/top_level.txt
tolkein-0.5.0.dist-info/RECORD
